{"name":"Gameproject","tagline":"Old school computer rpg game project.","body":"### Old school rpg game project \r\nThis is a project to create a Might and Magic (the old ones, not the heroes series) type game where the game world, town, dungeons and NPCs would all be randomly generated on each new game. World of different size could be generated.\r\n\r\n![Exploring a map. ](https://gillesleblanc.files.wordpress.com/2013/04/gameproject1.png?w=640&h=501)\r\n\r\n### Features\r\n\r\n* Procedural content generation\r\n    * Randomly generated world maps\r\n    * Randomly generated city maps\r\n    * Randomly generated dungeon maps\r\n    * Randomly generated names, npc's, treasure, quests, shops, ...\r\n* First person 2d style view\r\n* Runs on Ruby\r\n\r\n### Getting started\r\nFrom the root dir you can call map_explorer to explore map.\r\n\r\nFrom the City dir you can call city_map_output to generate a sample city and see it represented as an image.\r\n\r\nFrom the MapGenerator dir you can call map_output to generate a random world map and see it represented as an image.\r\n\r\nFrom the RandomNameGeneration dir you can call either random_name_generator_test, establishment_name_generator_test or place_name_generator_test to see some random names.\r\n\r\nFinally from the Rules dir you can call battle_coordinator to test out the rules engine.\r\n\r\n### Want to help out?\r\nFeel free to fork and send pull requests. If you aren't sure about using GitHub and you still want to contribute, feel free to contact me directly: gilles.leblanc (at) gmail.com\r\n\r\n![Generated world map](http://gillesleblanc.files.wordpress.com/2013/02/snow_cities_and_caves1.png)","google":"","note":"Don't delete this file! It's used internally to help with page regeneration."}